README.txt
setup.cfg
setup.py
docs/HISTORY.txt
docs/INSTALL.txt
docs/LICENSE.GPL
docs/LICENSE.txt
redturtle/__init__.py
redturtle.fss.egg-info/PKG-INFO
redturtle.fss.egg-info/SOURCES.txt
redturtle.fss.egg-info/dependency_links.txt
redturtle.fss.egg-info/entry_points.txt
redturtle.fss.egg-info/namespace_packages.txt
redturtle.fss.egg-info/not-zip-safe
redturtle.fss.egg-info/requires.txt
redturtle.fss.egg-info/top_level.txt
redturtle/fss/__init__.py
redturtle/fss/atct.zcml
redturtle/fss/config.py
redturtle/fss/configure.zcml
redturtle/fss/tests.py
redturtle/fss/version.txt