Metadata-Version: 1.0
Name: redturtle.fss
Version: 1.0.1
Summary: Simply apply FileSystemStorage strategies (iw.fss) to basic Plone content types.
Home-page: https://code.redturtle.it/svn/redturtle/redturtle.fss
Author: RedTurtle Technology
Author-email: info@redturtle.net
License: GPL
Keywords: iw fss plone storage file image
Platform: UNKNOWN
Classifier: Framework :: Plone
Classifier: Programming Language :: Python
Classifier: Topic :: Software Development :: Libraries :: Python Modules
